nuget_package_scanner/__init__.py
nuget_package_scanner/__main__.py
nuget_package_scanner/app.py
nuget_package_scanner/async_utils.py
nuget_package_scanner/github_search.py
nuget_package_scanner/smart_client.py
nuget_package_scanner/nuget/__init__.py
nuget_package_scanner/nuget/date_util.py
nuget_package_scanner/nuget/nuget.py
nuget_package_scanner/nuget/nuget_config.py
nuget_package_scanner/nuget/nuget_server.py
nuget_package_scanner/nuget/registrations.py
nuget_package_scanner/nuget/registrations_version.py
nuget_package_scanner/nuget/version_util.py
tests/__init__.py
tests/app_test.py
tests/date_util_test.py
tests/nuget_version_util_test.py
tests/nugetconfig_package_test.py
tests/nugetconfig_packagecontainer_test.py
tests/registrations_test.py
tests/registrations_version_config_test.py
tests/smart_client_test.py
tests/sampledata/__init__.py
nuget_package_scanner-0.0.6.dist-info/LICENSE
nuget_package_scanner-0.0.6.dist-info/METADATA
nuget_package_scanner-0.0.6.dist-info/WHEEL
nuget_package_scanner-0.0.6.dist-info/top_level.txt
nuget_package_scanner-0.0.6.dist-info/RECORD
