Metadata-Version: 2.1
Name: nuget-package-scanner
Version: 0.0.6
Summary: Scans a github org for Nuget dependencies and builds a currency report
Home-page: https://github.com/doneholmes/nuget-package-scanner
Author: Donnie Holmes
Author-email: donnieh@gmail.com
License: UNKNOWN
Keywords: nuget github org dependencies currency report
Platform: UNKNOWN
Classifier: Programming Language :: Python :: 3
Classifier: License :: OSI Approved :: MIT License
Classifier: Operating System :: OS Independent
Requires-Python: >=3.8.2
Requires-Dist: aiohttp (<4,>=3)
Requires-Dist: cchardet (>=2.1.6)
Requires-Dist: aiodns (>=2.0.0)
Requires-Dist: async-lru (>=1.0.2)
Requires-Dist: lxml (>=4.5.1)
Requires-Dist: tenacity (>=6.2.0)
